AndroidGradleChajianZhongwenZhinan/README.md
AndroidGradleChajianZhongwenZhinan/__init__.py
AndroidGradleChajianZhongwenZhinan/__main__.py
AndroidGradleChajianZhongwenZhinan/file.epub
AndroidGradleChajianZhongwenZhinan/index.html
AndroidGradleChajianZhongwenZhinan/css/__init__.py
AndroidGradleChajianZhongwenZhinan/css/annotations.css
AndroidGradleChajianZhongwenZhinan/css/main.css
AndroidGradleChajianZhongwenZhinan/css/normalize.css
AndroidGradleChajianZhongwenZhinan/css/popup.css
AndroidGradleChajianZhongwenZhinan/font/__init__.py
AndroidGradleChajianZhongwenZhinan/font/fontello.eot
AndroidGradleChajianZhongwenZhinan/font/fontello.svg
AndroidGradleChajianZhongwenZhinan/font/fontello.ttf
AndroidGradleChajianZhongwenZhinan/font/fontello.woff
AndroidGradleChajianZhongwenZhinan/img/__init__.py
AndroidGradleChajianZhongwenZhinan/img/annotator-glyph-sprite.png
AndroidGradleChajianZhongwenZhinan/img/annotator-icon-sprite.png
AndroidGradleChajianZhongwenZhinan/img/apple-touch-icon.png
AndroidGradleChajianZhongwenZhinan/img/cancelfullscreen.png
AndroidGradleChajianZhongwenZhinan/img/close.png
AndroidGradleChajianZhongwenZhinan/img/fullscreen.png
AndroidGradleChajianZhongwenZhinan/img/loader.gif
AndroidGradleChajianZhongwenZhinan/img/menu-icon.png
AndroidGradleChajianZhongwenZhinan/img/save.png
AndroidGradleChajianZhongwenZhinan/img/saved.png
AndroidGradleChajianZhongwenZhinan/img/settings-s.png
AndroidGradleChajianZhongwenZhinan/img/settings.png
AndroidGradleChajianZhongwenZhinan/img/star.png
AndroidGradleChajianZhongwenZhinan/js/__init__.py
AndroidGradleChajianZhongwenZhinan/js/epub.js
AndroidGradleChajianZhongwenZhinan/js/epub.min.js
AndroidGradleChajianZhongwenZhinan/js/epub.min.map
AndroidGradleChajianZhongwenZhinan/js/hooks.min.js
AndroidGradleChajianZhongwenZhinan/js/hooks.min.map
AndroidGradleChajianZhongwenZhinan/js/reader.js
AndroidGradleChajianZhongwenZhinan/js/reader.js.map
AndroidGradleChajianZhongwenZhinan/js/reader.min.js
android_gradle_chajian_zhongwen_zhinan-2024.3.3.0.dist-info/METADATA
android_gradle_chajian_zhongwen_zhinan-2024.3.3.0.dist-info/WHEEL
android_gradle_chajian_zhongwen_zhinan-2024.3.3.0.dist-info/entry_points.txt
android_gradle_chajian_zhongwen_zhinan-2024.3.3.0.dist-info/top_level.txt
android_gradle_chajian_zhongwen_zhinan-2024.3.3.0.dist-info/RECORD
